sparsesketch/__init__.py
sparsesketch/preprocessing.py
sparsesketch/sampling.py
sparsesketch/utils.py
sparsesketch-0.1.0.dist-info/licenses/LICENSE
sparsesketch-0.1.0.dist-info/METADATA
sparsesketch-0.1.0.dist-info/WHEEL
sparsesketch-0.1.0.dist-info/top_level.txt
sparsesketch-0.1.0.dist-info/RECORD
