Metadata-Version: 2.4
Name: sparsesketch
Version: 0.1.0
Summary: A Python package for fast sketching with applications on flow cytometry and scRNA-seq data, focusing on retaining rare cell populations.
Author-email: Ehsan Karimiara <e.karimiara@gmail.com>
License-Expression: MIT
Project-URL: Homepage, https://github.com/EhsanKA/sparsesketch
Requires-Python: >=3.10
License-File: LICENSE
Requires-Dist: numpy>=1.24
Requires-Dist: pandas
Requires-Dist: scikit-learn
Dynamic: license-file
